sqlalchemy_bigquery/__init__.py
sqlalchemy_bigquery/_helpers.py
sqlalchemy_bigquery/_struct.py
sqlalchemy_bigquery/_types.py
sqlalchemy_bigquery/base.py
sqlalchemy_bigquery/geography.py
sqlalchemy_bigquery/parse_url.py
sqlalchemy_bigquery/requirements.py
sqlalchemy_bigquery/version.py
sqlalchemy_bigquery_calista-1.10.0.dist-info/AUTHORS
sqlalchemy_bigquery_calista-1.10.0.dist-info/LICENSE
sqlalchemy_bigquery_calista-1.10.0.dist-info/METADATA
sqlalchemy_bigquery_calista-1.10.0.dist-info/WHEEL
sqlalchemy_bigquery_calista-1.10.0.dist-info/entry_points.txt
sqlalchemy_bigquery_calista-1.10.0.dist-info/top_level.txt
sqlalchemy_bigquery_calista-1.10.0.dist-info/RECORD
