Metadata-Version: 2.1
Name: sqlalchemy-bigquery-calista
Version: 1.10.0
Summary: SQLAlchemy dialect for BigQuery
Home-page: https://github.com/googleapis/python-bigquery-sqlalchemy
Author: The Sqlalchemy-Bigquery Authors
Author-email: googleapis-packages@google.com
Keywords: bigquery,sqlalchemy
Platform: Posix; MacOS X; Windows
Classifier: Development Status :: 5 - Production/Stable
Classifier: Intended Audience :: Developers
Classifier: License :: OSI Approved :: MIT License
Classifier: Programming Language :: Python
Classifier: Programming Language :: Python :: 3
Classifier: Programming Language :: Python :: 3.8
Classifier: Programming Language :: Python :: 3.9
Classifier: Programming Language :: Python :: 3.10
Classifier: Programming Language :: Python :: 3.11
Classifier: Programming Language :: Python :: 3.12
Classifier: Operating System :: OS Independent
Classifier: Topic :: Database :: Front-Ends
Obsoletes: pybigquery
Requires-Python: >=3.8, <3.13
License-File: LICENSE
License-File: AUTHORS
Requires-Dist: google-api-core !=2.0.*,!=2.1.*,!=2.2.*,!=2.3.0,<3.0.0dev,>=1.31.5
Requires-Dist: google-auth <3.0.0dev,>=1.25.0
Requires-Dist: google-cloud-bigquery <4.0.0dev,>=3.3.6
Requires-Dist: packaging
Requires-Dist: sqlalchemy >=2.0.29
Provides-Extra: alembic
Requires-Dist: alembic ; extra == 'alembic'
Provides-Extra: all
Requires-Dist: GeoAlchemy2 ; extra == 'all'
Requires-Dist: pytz ; extra == 'all'
Requires-Dist: google-cloud-bigquery-storage <3.0.0dev,>=2.0.0 ; extra == 'all'
Requires-Dist: shapely ; extra == 'all'
Requires-Dist: grpcio <2.0dev,>=1.47.0 ; extra == 'all'
Requires-Dist: packaging ; extra == 'all'
Requires-Dist: pyarrow >=3.0.0 ; extra == 'all'
Requires-Dist: alembic ; extra == 'all'
Requires-Dist: grpcio <2.0dev,>=1.49.1 ; (python_version >= "3.11") and extra == 'all'
Provides-Extra: bqstorage
Requires-Dist: google-cloud-bigquery-storage <3.0.0dev,>=2.0.0 ; extra == 'bqstorage'
Requires-Dist: grpcio <2.0dev,>=1.47.0 ; extra == 'bqstorage'
Requires-Dist: pyarrow >=3.0.0 ; extra == 'bqstorage'
Requires-Dist: grpcio <2.0dev,>=1.49.1 ; (python_version >= "3.11") and extra == 'bqstorage'
Provides-Extra: geography
Requires-Dist: GeoAlchemy2 ; extra == 'geography'
Requires-Dist: shapely ; extra == 'geography'
Provides-Extra: tests
Requires-Dist: packaging ; extra == 'tests'
Requires-Dist: pytz ; extra == 'tests'
